{
    "Id": "224075c7a0b64ef298c5ddee4dc048f3",
    "RecognitionStatus": "Success",
    "Offset": 3100000,
    "Duration": 192500000,
    "Channel": 0,
    "DisplayText": "An American dog, a Polish dog and a Soviet dog sit together. The American dog says In my country, if you bark long enough, you will be heard and given some meat. The Polish dog replies, What is meat? The Soviet dog says what is bark?",
    "SNR": 31.302134,
    "NBest": [
        {
            "Confidence": 0.9733869,
            "Lexical": "an american dog a polish dog and a soviet dog sit together the american dog says in my country if you bark long enough you will be heard and given some meat the polish dog replies what is meat the soviet dog says what is bark",
            "ITN": "an american dog a polish dog and a soviet dog sit together the american dog says in my country if you bark long enough you will be heard and given some meat the polish dog replies what is meat the soviet dog says what is bark",
            "MaskedITN": "an american dog a polish dog and a soviet dog sit together the american dog says in my country if you bark long enough you will be heard and given some meat the polish dog replies what is meat the soviet dog says what is bark",
            "Display": "An American dog, a Polish dog and a Soviet dog sit together. The American dog says In my country, if you bark long enough, you will be heard and given some meat. The Polish dog replies, What is meat? The Soviet dog says what is bark?",
            "PronunciationAssessment": {
                "AccuracyScore": 95.0,
                "FluencyScore": 92.0,
                "CompletenessScore": 98.0,
                "PronScore": 93.8
            },
            "Words": [
                {
                    "Word": "an",
                    "Offset": 3100000,
                    "Duration": 3300000,
                    "PronunciationAssessment": {
                        "AccuracyScore": 100.0,
                        "ErrorType": "None"
                    },
                    "Syllables": [
                        {
                            "Syllable": "aen",
                            "Grapheme": "an",
                            "PronunciationAssessment": {
                                "AccuracyScore": 100.0
                            },
                            "Offset": 3100000,
                            "Duration": 3300000
                        }
                    ],
                    "Phonemes": [
                        {
                            "Phoneme": "ae",
                            "PronunciationAssessment": {
                                "AccuracyScore": 100.0
                            },
                            "Offset": 3100000,
                            "Duration": 2100000
                        },
                        {
                            "Phoneme": "n",
                            "PronunciationAssessment": {
                                "AccuracyScore": 100.0
                            },
                            "Offset": 5300000,
                            "Duration": 1100000
                        }
                    ]
                },
                {
                    "Word": "american",
                    "Offset": 6500000,
                    "Duration": 5500000,
                    "PronunciationAssessment": {
                        "AccuracyScore": 100.0,
                        "ErrorType": "None"
                    },
                    "Syllables": [
                        {
                            "Syllable": "ax",
                            "Grapheme": "a",
                            "PronunciationAssessment": {
                                "AccuracyScore": 100.0
                            },
                            "Offset": 6500000,
                            "Duration": 900000
                        },
                        {
                            "Syllable": "meh",
                            "Grapheme": "mer",
                            "PronunciationAssessment": {
                                "AccuracyScore": 100.0
                            },
                            "Offset": 7500000,
                            "Duration": 1900000
                        },
                        {
                            "Syllable": "rih",
                            "Grapheme": "i",
                            "PronunciationAssessment": {
                                "AccuracyScore": 100.0
                            },
                            "Offset": 9500000,
                            "Duration": 1100000
                        },
                        {
                            "Syllable": "kaxn",
                            "Grapheme": "can",
                            "PronunciationAssessment": {
                                "AccuracyScore": 100.0
                            },
                            "Offset": 10700000,
                            "Duration": 1300000
                        }
                    ],
                    "Phonemes": [
                        {
                            "Phoneme": "ax",
                            "PronunciationAssessment": {
                                "AccuracyScore": 100.0
                            },
                            "Offset": 6500000,
                            "Duration": 900000
                        },
                        {
                            "Phoneme": "m",
                            "PronunciationAssessment": {
                                "AccuracyScore": 100.0
                            },
                            "Offset": 7500000,
                            "Duration": 1100000
                        },
                        {
                            "Phoneme": "eh",
                            "PronunciationAssessment": {
                                "AccuracyScore": 100.0
                            },
                            "Offset": 8700000,
                            "Duration": 700000
                        },
                        {
                            "Phoneme": "r",
                            "PronunciationAssessment": {
                                "AccuracyScore": 100.0
                            },
                            "Offset": 9500000,
                            "Duration": 500000
                        },
                        {
                            "Phoneme": "ih",
                            "PronunciationAssessment": {
                                "AccuracyScore": 100.0
                            },
                            "Offset": 10100000,
                            "Duration": 500000
                        },
                        {
                            "Phoneme": "k",
                            "PronunciationAssessment": {
                                "AccuracyScore": 100.0
                            },
                            "Offset": 10700000,
                            "Duration": 500000
                        },
                        {
                            "Phoneme": "ax",
                            "PronunciationAssessment": {
                                "AccuracyScore": 100.0
                            },
                            "Offset": 11300000,
                            "Duration": 300000
                        },
                        {
                            "Phoneme": "n",
                            "PronunciationAssessment": {
                                "AccuracyScore": 100.0
                            },
                            "Offset": 11700000,
                            "Duration": 300000
                        }
                    ]
                },
                {
                    "Word": "dog",
                    "Offset": 12100000,
                    "Duration": 4900000,
                    "PronunciationAssessment": {
                        "AccuracyScore": 100.0,
                        "ErrorType": "None"
                    },
                    "Syllables": [
                        {
                            "Syllable": "daog",
                            "Grapheme": "dog",
                            "PronunciationAssessment": {
                                "AccuracyScore": 100.0
                            },
                            "Offset": 12100000,
                            "Duration": 4900000
                        }
                    ],
                    "Phonemes": [
                        {
                            "Phoneme": "d",
                            "PronunciationAssessment": {
                                "AccuracyScore": 100.0
                            },
                            "Offset": 12100000,
                            "Duration": 900000
                        },
                        {
                            "Phoneme": "ao",
                            "PronunciationAssessment": {
                                "AccuracyScore": 100.0
                            },
                            "Offset": 13100000,
                            "Duration": 1900000
                        },
                        {
                            "Phoneme": "g",
                            "PronunciationAssessment": {
                                "AccuracyScore": 100.0
                            },
                            "Offset": 15100000,
                            "Duration": 1900000
                        }
                    ]
                },
                {
                    "Word": "a",
                    "Offset": 17900000,
                    "Duration": 1900000,
                    "PronunciationAssessment": {
                        "AccuracyScore": 100.0,
                        "ErrorType": "None"
                    },
                    "Syllables": [
                        {
                            "Syllable": "ax",
                            "Grapheme": "a",
                            "PronunciationAssessment": {
                                "AccuracyScore": 100.0
                            },
                            "Offset": 17900000,
                            "Duration": 1900000
                        }
                    ],
                    "Phonemes": [
                        {
                            "Phoneme": "ax",
                            "PronunciationAssessment": {
                                "AccuracyScore": 100.0
                            },
                            "Offset": 17900000,
                            "Duration": 1900000
                        }
                    ]
                },
                {
                    "Word": "polish",
                    "Offset": 19900000,
                    "Duration": 6900000,
                    "PronunciationAssessment": {
                        "AccuracyScore": 94.0,
                        "ErrorType": "None"
                    },
                    "Syllables": [
                        {
                            "Syllable": "pow",
                            "PronunciationAssessment": {
                                "AccuracyScore": 100.0
                            },
                            "Offset": 19900000,
                            "Duration": 3500000
                        },
                        {
                            "Syllable": "lihsh",
                            "PronunciationAssessment": {
                                "AccuracyScore": 92.0
                            },
                            "Offset": 23500000,
                            "Duration": 3300000
                        }
                    ],
                    "Phonemes": [
                        {
                            "Phoneme": "p",
                            "PronunciationAssessment": {
                                "AccuracyScore": 100.0
                            },
                            "Offset": 19900000,
                            "Duration": 1900000
                        },
                        {
                            "Phoneme": "ow",
                            "PronunciationAssessment": {
                                "AccuracyScore": 100.0
                            },
                            "Offset": 21900000,
                            "Duration": 1500000
                        },
                        {
                            "Phoneme": "l",
                            "PronunciationAssessment": {
                                "AccuracyScore": 78.0
                            },
                            "Offset": 23500000,
                            "Duration": 1200000
                        },
                        {
                            "Phoneme": "ih",
                            "PronunciationAssessment": {
                                "AccuracyScore": 100.0
                            },
                            "Offset": 24800000,
                            "Duration": 400000
                        },
                        {
                            "Phoneme": "sh",
                            "PronunciationAssessment": {
                                "AccuracyScore": 100.0
                            },
                            "Offset": 25300000,
                            "Duration": 1500000
                        }
                    ]
                },
                {
                    "Word": "dog",
                    "Offset": 26900000,
                    "Duration": 4200000,
                    "PronunciationAssessment": {
                        "AccuracyScore": 76.0,
                        "ErrorType": "None"
                    },
                    "Syllables": [
                        {
                            "Syllable": "daog",
                            "Grapheme": "dog",
                            "PronunciationAssessment": {
                                "AccuracyScore": 85.0
                            },
                            "Offset": 26900000,
                            "Duration": 4200000
                        }
                    ],
                    "Phonemes": [
                        {
                            "Phoneme": "d",
                            "PronunciationAssessment": {
                                "AccuracyScore": 57.0
                            },
                            "Offset": 26900000,
                            "Duration": 700000
                        },
                        {
                            "Phoneme": "ao",
                            "PronunciationAssessment": {
                                "AccuracyScore": 70.0
                            },
                            "Offset": 27700000,
                            "Duration": 900000
                        },
                        {
                            "Phoneme": "g",
                            "PronunciationAssessment": {
                                "AccuracyScore": 100.0
                            },
                            "Offset": 28700000,
                            "Duration": 2400000
                        }
                    ]
                },
                {
                    "Word": "and",
                    "Offset": 31900000,
                    "Duration": 2100000,
                    "PronunciationAssessment": {
                        "AccuracyScore": 96.0,
                        "ErrorType": "None"
                    },
                    "Syllables": [
                        {
                            "Syllable": "axnd",
                            "Grapheme": "and",
                            "PronunciationAssessment": {
                                "AccuracyScore": 85.0
                            },
                            "Offset": 31900000,
                            "Duration": 2100000
                        }
                    ],
                    "Phonemes": [
                        {
                            "Phoneme": "ax",
                            "PronunciationAssessment": {
                                "AccuracyScore": 88.0
                            },
                            "Offset": 31900000,
                            "Duration": 1300000
                        },
                        {
                            "Phoneme": "n",
                            "PronunciationAssessment": {
                                "AccuracyScore": 83.0
                            },
                            "Offset": 33300000,
                            "Duration": 300000
                        },
                        {
                            "Phoneme": "d",
                            "PronunciationAssessment": {
                                "AccuracyScore": 77.0
                            },
                            "Offset": 33700000,
                            "Duration": 300000
                        }
                    ]
                },
                {
                    "Word": "a",
                    "Offset": 34100000,
                    "Duration": 500000,
                    "PronunciationAssessment": {
                        "AccuracyScore": 100.0,
                        "ErrorType": "None"
                    },
                    "Syllables": [
                        {
                            "Syllable": "ax",
                            "Grapheme": "a",
                            "PronunciationAssessment": {
                                "AccuracyScore": 100.0
                            },
                            "Offset": 34100000,
                            "Duration": 500000
                        }
                    ],
                    "Phonemes": [
                        {
                            "Phoneme": "ax",
                            "PronunciationAssessment": {
                                "AccuracyScore": 100.0
                            },
                            "Offset": 34100000,
                            "Duration": 500000
                        }
                    ]
                },
                {
                    "Word": "soviet",
                    "Offset": 34700000,
                    "Duration": 4700000,
                    "PronunciationAssessment": {
                        "AccuracyScore": 88.0,
                        "ErrorType": "None"
                    },
                    "Syllables": [
                        {
                            "Syllable": "sow",
                            "Grapheme": "so",
                            "PronunciationAssessment": {
                                "AccuracyScore": 82.0
                            },
                            "Offset": 34700000,
                            "Duration": 2300000
                        },
                        {
                            "Syllable": "viy",
                            "Grapheme": "vi",
                            "PronunciationAssessment": {
                                "AccuracyScore": 100.0
                            },
                            "Offset": 37100000,
                            "Duration": 1200000
                        },
                        {
                            "Syllable": "axt",
                            "Grapheme": "et",
                            "PronunciationAssessment": {
                                "AccuracyScore": 79.0
                            },
                            "Offset": 38400000,
                            "Duration": 1000000
                        }
                    ],
                    "Phonemes": [
                        {
                            "Phoneme": "s",
                            "PronunciationAssessment": {
                                "AccuracyScore": 82.0
                            },
                            "Offset": 34700000,
                            "Duration": 1500000
                        },
                        {
                            "Phoneme": "ow",
                            "PronunciationAssessment": {
                                "AccuracyScore": 82.0
                            },
                            "Offset": 36300000,
                            "Duration": 700000
                        },
                        {
                            "Phoneme": "v",
                            "PronunciationAssessment": {
                                "AccuracyScore": 100.0
                            },
                            "Offset": 37100000,
                            "Duration": 600000
                        },
                        {
                            "Phoneme": "iy",
                            "PronunciationAssessment": {
                                "AccuracyScore": 100.0
                            },
                            "Offset": 37800000,
                            "Duration": 500000
                        },
                        {
                            "Phoneme": "ax",
                            "PronunciationAssessment": {
                                "AccuracyScore": 100.0
                            },
                            "Offset": 38400000,
                            "Duration": 600000
                        },
                        {
                            "Phoneme": "t",
                            "PronunciationAssessment": {
                                "AccuracyScore": 42.0
                            },
                            "Offset": 39100000,
                            "Duration": 300000
                        }
                    ]
                },
                {
                    "Word": "dog",
                    "Offset": 39500000,
                    "Duration": 3100000,
                    "PronunciationAssessment": {
                        "AccuracyScore": 100.0,
                        "ErrorType": "None"
                    },
                    "Syllables": [
                        {
                            "Syllable": "daog",
                            "Grapheme": "dog",
                            "PronunciationAssessment": {
                                "AccuracyScore": 100.0
                            },
                            "Offset": 39500000,
                            "Duration": 3100000
                        }
                    ],
                    "Phonemes": [
                        {
                            "Phoneme": "d",
                            "PronunciationAssessment": {
                                "AccuracyScore": 100.0
                            },
                            "Offset": 39500000,
                            "Duration": 500000
                        },
                        {
                            "Phoneme": "ao",
                            "PronunciationAssessment": {
                                "AccuracyScore": 100.0
                            },
                            "Offset": 40100000,
                            "Duration": 1100000
                        },
                        {
                            "Phoneme": "g",
                            "PronunciationAssessment": {
                                "AccuracyScore": 100.0
                            },
                            "Offset": 41300000,
                            "Duration": 1300000
                        }
                    ]
                },
                {
                    "Word": "sit",
                    "Offset": 42700000,
                    "Duration": 3200000,
                    "PronunciationAssessment": {
                        "AccuracyScore": 88.0,
                        "ErrorType": "None"
                    },
                    "Syllables": [
                        {
                            "Syllable": "siht",
                            "Grapheme": "sit",
                            "PronunciationAssessment": {
                                "AccuracyScore": 79.0
                            },
                            "Offset": 42700000,
                            "Duration": 3200000
                        }
                    ],
                    "Phonemes": [
                        {
                            "Phoneme": "s",
                            "PronunciationAssessment": {
                                "AccuracyScore": 85.0
                            },
                            "Offset": 42700000,
                            "Duration": 1500000
                        },
                        {
                            "Phoneme": "ih",
                            "PronunciationAssessment": {
                                "AccuracyScore": 72.0
                            },
                            "Offset": 44300000,
                            "Duration": 800000
                        },
                        {
                            "Phoneme": "t",
                            "PronunciationAssessment": {
                                "AccuracyScore": 75.0
                            },
                            "Offset": 45200000,
                            "Duration": 700000
                        }
                    ]
                },
                {
                    "Word": "together",
                    "Offset": 46000000,
                    "Duration": 6000000,
                    "PronunciationAssessment": {
                        "AccuracyScore": 98.0,
                        "ErrorType": "None"
                    },
                    "Syllables": [
                        {
                            "Syllable": "tax",
                            "Grapheme": "to",
                            "PronunciationAssessment": {
                                "AccuracyScore": 91.0
                            },
                            "Offset": 46000000,
                            "Duration": 600000
                        },
                        {
                            "Syllable": "geh",
                            "Grapheme": "geth",
                            "PronunciationAssessment": {
                                "AccuracyScore": 100.0
                            },
                            "Offset": 46700000,
                            "Duration": 1900000
                        },
                        {
                            "Syllable": "dhaxr",
                            "Grapheme": "er",
                            "PronunciationAssessment": {
                                "AccuracyScore": 92.0
                            },
                            "Offset": 48700000,
                            "Duration": 3300000
                        }
                    ],
                    "Phonemes": [
                        {
                            "Phoneme": "t",
                            "PronunciationAssessment": {
                                "AccuracyScore": 80.0
                            },
                            "Offset": 46000000,
                            "Duration": 200000
                        },
                        {
                            "Phoneme": "ax",
                            "PronunciationAssessment": {
                                "AccuracyScore": 100.0
                            },
                            "Offset": 46300000,
                            "Duration": 300000
                        },
                        {
                            "Phoneme": "g",
                            "PronunciationAssessment": {
                                "AccuracyScore": 100.0
                            },
                            "Offset": 46700000,
                            "Duration": 900000
                        },
                        {
                            "Phoneme": "eh",
                            "PronunciationAssessment": {
                                "AccuracyScore": 100.0
                            },
                            "Offset": 47700000,
                            "Duration": 900000
                        },
                        {
                            "Phoneme": "dh",
                            "PronunciationAssessment": {
                                "AccuracyScore": 100.0
                            },
                            "Offset": 48700000,
                            "Duration": 700000
                        },
                        {
                            "Phoneme": "ax",
                            "PronunciationAssessment": {
                                "AccuracyScore": 100.0
                            },
                            "Offset": 49500000,
                            "Duration": 900000
                        },
                        {
                            "Phoneme": "r",
                            "PronunciationAssessment": {
                                "AccuracyScore": 84.0
                            },
                            "Offset": 50500000,
                            "Duration": 1500000
                        }
                    ]
                },
                {
                    "Word": "the",
                    "Offset": 57000000,
                    "Duration": 2000000,
                    "PronunciationAssessment": {
                        "AccuracyScore": 100.0,
                        "ErrorType": "None"
                    },
                    "Syllables": [
                        {
                            "Syllable": "dhax",
                            "Grapheme": "the",
                            "PronunciationAssessment": {
                                "AccuracyScore": 100.0
                            },
                            "Offset": 57000000,
                            "Duration": 2000000
                        }
                    ],
                    "Phonemes": [
                        {
                            "Phoneme": "dh",
                            "PronunciationAssessment": {
                                "AccuracyScore": 100.0
                            },
                            "Offset": 57000000,
                            "Duration": 1200000
                        },
                        {
                            "Phoneme": "ax",
                            "PronunciationAssessment": {
                                "AccuracyScore": 100.0
                            },
                            "Offset": 58300000,
                            "Duration": 700000
                        }
                    ]
                },
                {
                    "Word": "american",
                    "Offset": 59100000,
                    "Duration": 4900000,
                    "PronunciationAssessment": {
                        "AccuracyScore": 100.0,
                        "ErrorType": "None"
                    },
                    "Syllables": [
                        {
                            "Syllable": "ax",
                            "Grapheme": "a",
                            "PronunciationAssessment": {
                                "AccuracyScore": 100.0
                            },
                            "Offset": 59100000,
                            "Duration": 700000
                        },
                        {
                            "Syllable": "meh",
                            "Grapheme": "mer",
                            "PronunciationAssessment": {
                                "AccuracyScore": 100.0
                            },
                            "Offset": 59900000,
                            "Duration": 1500000
                        },
                        {
                            "Syllable": "rih",
                            "Grapheme": "i",
                            "PronunciationAssessment": {
                                "AccuracyScore": 100.0
                            },
                            "Offset": 61500000,
                            "Duration": 1100000
                        },
                        {
                            "Syllable": "kaxn",
                            "Grapheme": "can",
                            "PronunciationAssessment": {
                                "AccuracyScore": 100.0
                            },
                            "Offset": 62700000,
                            "Duration": 1300000
                        }
                    ],
                    "Phonemes": [
                        {
                            "Phoneme": "ax",
                            "PronunciationAssessment": {
                                "AccuracyScore": 100.0
                            },
                            "Offset": 59100000,
                            "Duration": 700000
                        },
                        {
                            "Phoneme": "m",
                            "PronunciationAssessment": {
                                "AccuracyScore": 100.0
                            },
                            "Offset": 59900000,
                            "Duration": 500000
                        },
                        {
                            "Phoneme": "eh",
                            "PronunciationAssessment": {
                                "AccuracyScore": 100.0
                            },
                            "Offset": 60500000,
                            "Duration": 900000
                        },
                        {
                            "Phoneme": "r",
                            "PronunciationAssessment": {
                                "AccuracyScore": 100.0
                            },
                            "Offset": 61500000,
                            "Duration": 300000
                        },
                        {
                            "Phoneme": "ih",
                            "PronunciationAssessment": {
                                "AccuracyScore": 100.0
                            },
                            "Offset": 61900000,
                            "Duration": 700000
                        },
                        {
                            "Phoneme": "k",
                            "PronunciationAssessment": {
                                "AccuracyScore": 100.0
                            },
                            "Offset": 62700000,
                            "Duration": 400000
                        },
                        {
                            "Phoneme": "ax",
                            "PronunciationAssessment": {
                                "AccuracyScore": 100.0
                            },
                            "Offset": 63200000,
                            "Duration": 400000
                        },
                        {
                            "Phoneme": "n",
                            "PronunciationAssessment": {
                                "AccuracyScore": 100.0
                            },
                            "Offset": 63700000,
                            "Duration": 300000
                        }
                    ]
                },
                {
                    "Word": "dog",
                    "Offset": 64100000,
                    "Duration": 2900000,
                    "PronunciationAssessment": {
                        "AccuracyScore": 100.0,
                        "ErrorType": "None"
                    },
                    "Syllables": [
                        {
                            "Syllable": "daog",
                            "Grapheme": "dog",
                            "PronunciationAssessment": {
                                "AccuracyScore": 100.0
                            },
                            "Offset": 64100000,
                            "Duration": 2900000
                        }
                    ],
                    "Phonemes": [
                        {
                            "Phoneme": "d",
                            "PronunciationAssessment": {
                                "AccuracyScore": 100.0
                            },
                            "Offset": 64100000,
                            "Duration": 900000
                        },
                        {
                            "Phoneme": "ao",
                            "PronunciationAssessment": {
                                "AccuracyScore": 100.0
                            },
                            "Offset": 65100000,
                            "Duration": 700000
                        },
                        {
                            "Phoneme": "g",
                            "PronunciationAssessment": {
                                "AccuracyScore": 100.0
                            },
                            "Offset": 65900000,
                            "Duration": 1100000
                        }
                    ]
                },
                {
                    "Word": "says",
                    "Offset": 67100000,
                    "Duration": 5500000,
                    "PronunciationAssessment": {
                        "AccuracyScore": 100.0,
                        "ErrorType": "None"
                    },
                    "Syllables": [
                        {
                            "Syllable": "sehz",
                            "Grapheme": "says",
                            "PronunciationAssessment": {
                                "AccuracyScore": 100.0
                            },
                            "Offset": 67100000,
                            "Duration": 5500000
                        }
                    ],
                    "Phonemes": [
                        {
                            "Phoneme": "s",
                            "PronunciationAssessment": {
                                "AccuracyScore": 100.0
                            },
                            "Offset": 67100000,
                            "Duration": 1300000
                        },
                        {
                            "Phoneme": "eh",
                            "PronunciationAssessment": {
                                "AccuracyScore": 100.0
                            },
                            "Offset": 68500000,
                            "Duration": 2100000
                        },
                        {
                            "Phoneme": "z",
                            "PronunciationAssessment": {
                                "AccuracyScore": 100.0
                            },
                            "Offset": 70700000,
                            "Duration": 1900000
                        }
                    ]
                },
                {
                    "Word": "in",
                    "Offset": 74800000,
                    "Duration": 2600000,
                    "PronunciationAssessment": {
                        "AccuracyScore": 100.0,
                        "ErrorType": "None"
                    },
                    "Syllables": [
                        {
                            "Syllable": "ihn",
                            "Grapheme": "in",
                            "PronunciationAssessment": {
                                "AccuracyScore": 100.0
                            },
                            "Offset": 74800000,
                            "Duration": 2600000
                        }
                    ],
                    "Phonemes": [
                        {
                            "Phoneme": "ih",
                            "PronunciationAssessment": {
                                "AccuracyScore": 100.0
                            },
                            "Offset": 74800000,
                            "Duration": 1400000
                        },
                        {
                            "Phoneme": "n",
                            "PronunciationAssessment": {
                                "AccuracyScore": 100.0
                            },
                            "Offset": 76300000,
                            "Duration": 1100000
                        }
                    ]
                },
                {
                    "Word": "my",
                    "Offset": 77500000,
                    "Duration": 2900000,
                    "PronunciationAssessment": {
                        "AccuracyScore": 100.0,
                        "ErrorType": "None"
                    },
                    "Syllables": [
                        {
                            "Syllable": "may",
                            "Grapheme": "my",
                            "PronunciationAssessment": {
                                "AccuracyScore": 100.0
                            },
                            "Offset": 77500000,
                            "Duration": 2900000
                        }
                    ],
                    "Phonemes": [
                        {
                            "Phoneme": "m",
                            "PronunciationAssessment": {
                                "AccuracyScore": 100.0
                            },
                            "Offset": 77500000,
                            "Duration": 700000
                        },
                        {
                            "Phoneme": "ay",
                            "PronunciationAssessment": {
                                "AccuracyScore": 100.0
                            },
                            "Offset": 78300000,
                            "Duration": 2100000
                        }
                    ]
                },
                {
                    "Word": "country",
                    "Offset": 80500000,
                    "Duration": 7300000,
                    "PronunciationAssessment": {
                        "AccuracyScore": 98.0,
                        "ErrorType": "None"
                    },
                    "Syllables": [
                        {
                            "Syllable": "kahn",
                            "Grapheme": "coun",
                            "PronunciationAssessment": {
                                "AccuracyScore": 95.0
                            },
                            "Offset": 80500000,
                            "Duration": 2700000
                        },
                        {
                            "Syllable": "triy",
                            "Grapheme": "try",
                            "PronunciationAssessment": {
                                "AccuracyScore": 99.0
                            },
                            "Offset": 83300000,
                            "Duration": 4500000
                        }
                    ],
                    "Phonemes": [
                        {
                            "Phoneme": "k",
                            "PronunciationAssessment": {
                                "AccuracyScore": 89.0
                            },
                            "Offset": 80500000,
                            "Duration": 1100000
                        },
                        {
                            "Phoneme": "ah",
                            "PronunciationAssessment": {
                                "AccuracyScore": 100.0
                            },
                            "Offset": 81700000,
                            "Duration": 900000
                        },
                        {
                            "Phoneme": "n",
                            "PronunciationAssessment": {
                                "AccuracyScore": 100.0
                            },
                            "Offset": 82700000,
                            "Duration": 500000
                        },
                        {
                            "Phoneme": "t",
                            "PronunciationAssessment": {
                                "AccuracyScore": 100.0
                            },
                            "Offset": 83300000,
                            "Duration": 1100000
                        },
                        {
                            "Phoneme": "r",
                            "PronunciationAssessment": {
                                "AccuracyScore": 100.0
                            },
                            "Offset": 84500000,
                            "Duration": 900000
                        },
                        {
                            "Phoneme": "iy",
                            "PronunciationAssessment": {
                                "AccuracyScore": 98.0
                            },
                            "Offset": 85500000,
                            "Duration": 2300000
                        }
                    ]
                },
                {
                    "Word": "if",
                    "Offset": 89800000,
                    "Duration": 3000000,
                    "PronunciationAssessment": {
                        "AccuracyScore": 100.0,
                        "ErrorType": "None"
                    },
                    "Syllables": [
                        {
                            "Syllable": "ihf",
                            "Grapheme": "if",
                            "PronunciationAssessment": {
                                "AccuracyScore": 100.0
                            },
                            "Offset": 89800000,
                            "Duration": 3000000
                        }
                    ],
                    "Phonemes": [
                        {
                            "Phoneme": "ih",
                            "PronunciationAssessment": {
                                "AccuracyScore": 100.0
                            },
                            "Offset": 89800000,
                            "Duration": 2200000
                        },
                        {
                            "Phoneme": "f",
                            "PronunciationAssessment": {
                                "AccuracyScore": 100.0
                            },
                            "Offset": 92100000,
                            "Duration": 700000
                        }
                    ]
                },
                {
                    "Word": "you",
                    "Offset": 92900000,
                    "Duration": 1500000,
                    "PronunciationAssessment": {
                        "AccuracyScore": 100.0,
                        "ErrorType": "None"
                    },
                    "Syllables": [
                        {
                            "Syllable": "yuw",
                            "Grapheme": "you",
                            "PronunciationAssessment": {
                                "AccuracyScore": 100.0
                            },
                            "Offset": 92900000,
                            "Duration": 1500000
                        }
                    ],
                    "Phonemes": [
                        {
                            "Phoneme": "y",
                            "PronunciationAssessment": {
                                "AccuracyScore": 100.0
                            },
                            "Offset": 92900000,
                            "Duration": 700000
                        },
                        {
                            "Phoneme": "uw",
                            "PronunciationAssessment": {
                                "AccuracyScore": 100.0
                            },
                            "Offset": 93700000,
                            "Duration": 700000
                        }
                    ]
                },
                {
                    "Word": "bark",
                    "Offset": 94500000,
                    "Duration": 3500000,
                    "PronunciationAssessment": {
                        "AccuracyScore": 98.0,
                        "ErrorType": "None"
                    },
                    "Syllables": [
                        {
                            "Syllable": "baark",
                            "Grapheme": "bark",
                            "PronunciationAssessment": {
                                "AccuracyScore": 93.0
                            },
                            "Offset": 94500000,
                            "Duration": 3500000
                        }
                    ],
                    "Phonemes": [
                        {
                            "Phoneme": "b",
                            "PronunciationAssessment": {
                                "AccuracyScore": 100.0
                            },
                            "Offset": 94500000,
                            "Duration": 1100000
                        },
                        {
                            "Phoneme": "aa",
                            "PronunciationAssessment": {
                                "AccuracyScore": 100.0
                            },
                            "Offset": 95700000,
                            "Duration": 1100000
                        },
                        {
                            "Phoneme": "r",
                            "PronunciationAssessment": {
                                "AccuracyScore": 100.0
                            },
                            "Offset": 96900000,
                            "Duration": 500000
                        },
                        {
                            "Phoneme": "k",
                            "PronunciationAssessment": {
                                "AccuracyScore": 59.0
                            },
                            "Offset": 97500000,
                            "Duration": 500000
                        }
                    ]
                },
                {
                    "Word": "long",
                    "Offset": 98100000,
                    "Duration": 4100000,
                    "PronunciationAssessment": {
                        "AccuracyScore": 100.0,
                        "ErrorType": "None"
                    },
                    "Syllables": [
                        {
                            "Syllable": "laong",
                            "Grapheme": "long",
                            "PronunciationAssessment": {
                                "AccuracyScore": 100.0
                            },
                            "Offset": 98100000,
                            "Duration": 4100000
                        }
                    ],
                    "Phonemes": [
                        {
                            "Phoneme": "l",
                            "PronunciationAssessment": {
                                "AccuracyScore": 100.0
                            },
                            "Offset": 98100000,
                            "Duration": 1500000
                        },
                        {
                            "Phoneme": "ao",
                            "PronunciationAssessment": {
                                "AccuracyScore": 100.0
                            },
                            "Offset": 99700000,
                            "Duration": 1300000
                        },
                        {
                            "Phoneme": "ng",
                            "PronunciationAssessment": {
                                "AccuracyScore": 100.0
                            },
                            "Offset": 101100000,
                            "Duration": 1100000
                        }
                    ]
                },
                {
                    "Word": "enough",
                    "Offset": 102300000,
                    "Duration": 6400000,
                    "PronunciationAssessment": {
                        "AccuracyScore": 82.0,
                        "ErrorType": "None"
                    },
                    "Syllables": [
                        {
                            "Syllable": "iy",
                            "Grapheme": "e",
                            "PronunciationAssessment": {
                                "AccuracyScore": 84.0
                            },
                            "Offset": 102300000,
                            "Duration": 300000
                        },
                        {
                            "Syllable": "nahf",
                            "Grapheme": "nough",
                            "PronunciationAssessment": {
                                "AccuracyScore": 73.0
                            },
                            "Offset": 102700000,
                            "Duration": 6000000
                        }
                    ],
                    "Phonemes": [
                        {
                            "Phoneme": "iy",
                            "PronunciationAssessment": {
                                "AccuracyScore": 84.0
                            },
                            "Offset": 102300000,
                            "Duration": 300000
                        },
                        {
                            "Phoneme": "n",
                            "PronunciationAssessment": {
                                "AccuracyScore": 100.0
                            },
                            "Offset": 102700000,
                            "Duration": 900000
                        },
                        {
                            "Phoneme": "ah",
                            "PronunciationAssessment": {
                                "AccuracyScore": 100.0
                            },
                            "Offset": 103700000,
                            "Duration": 1500000
                        },
                        {
                            "Phoneme": "f",
                            "PronunciationAssessment": {
                                "AccuracyScore": 53.0
                            },
                            "Offset": 105300000,
                            "Duration": 3400000
                        }
                    ]
                },
                {
                    "Word": "you",
                    "Offset": 109000000,
                    "Duration": 2800000,
                    "PronunciationAssessment": {
                        "AccuracyScore": 100.0,
                        "ErrorType": "None"
                    },
                    "Syllables": [
                        {
                            "Syllable": "yuw",
                            "Grapheme": "you",
                            "PronunciationAssessment": {
                                "AccuracyScore": 100.0
                            },
                            "Offset": 109000000,
                            "Duration": 2800000
                        }
                    ],
                    "Phonemes": [
                        {
                            "Phoneme": "y",
                            "PronunciationAssessment": {
                                "AccuracyScore": 100.0
                            },
                            "Offset": 109000000,
                            "Duration": 1800000
                        },
                        {
                            "Phoneme": "uw",
                            "PronunciationAssessment": {
                                "AccuracyScore": 100.0
                            },
                            "Offset": 110900000,
                            "Duration": 900000
                        }
                    ]
                },
                {
                    "Word": "will",
                    "Offset": 111900000,
                    "Duration": 1300000,
                    "PronunciationAssessment": {
                        "AccuracyScore": 100.0,
                        "ErrorType": "None"
                    },
                    "Syllables": [
                        {
                            "Syllable": "wihl",
                            "Grapheme": "will",
                            "PronunciationAssessment": {
                                "AccuracyScore": 100.0
                            },
                            "Offset": 111900000,
                            "Duration": 1300000
                        }
                    ],
                    "Phonemes": [
                        {
                            "Phoneme": "w",
                            "PronunciationAssessment": {
                                "AccuracyScore": 100.0
                            },
                            "Offset": 111900000,
                            "Duration": 300000
                        },
                        {
                            "Phoneme": "ih",
                            "PronunciationAssessment": {
                                "AccuracyScore": 100.0
                            },
                            "Offset": 112300000,
                            "Duration": 500000
                        },
                        {
                            "Phoneme": "l",
                            "PronunciationAssessment": {
                                "AccuracyScore": 100.0
                            },
                            "Offset": 112900000,
                            "Duration": 300000
                        }
                    ]
                },
                {
                    "Word": "be",
                    "Offset": 113300000,
                    "Duration": 1300000,
                    "PronunciationAssessment": {
                        "AccuracyScore": 100.0,
                        "ErrorType": "None"
                    },
                    "Syllables": [
                        {
                            "Syllable": "biy",
                            "Grapheme": "be",
                            "PronunciationAssessment": {
                                "AccuracyScore": 100.0
                            },
                            "Offset": 113300000,
                            "Duration": 1300000
                        }
                    ],
                    "Phonemes": [
                        {
                            "Phoneme": "b",
                            "PronunciationAssessment": {
                                "AccuracyScore": 100.0
                            },
                            "Offset": 113300000,
                            "Duration": 500000
                        },
                        {
                            "Phoneme": "iy",
                            "PronunciationAssessment": {
                                "AccuracyScore": 100.0
                            },
                            "Offset": 113900000,
                            "Duration": 700000
                        }
                    ]
                },
                {
                    "Word": "heard",
                    "Offset": 114700000,
                    "Duration": 6700000,
                    "PronunciationAssessment": {
                        "AccuracyScore": 92.0,
                        "ErrorType": "None"
                    },
                    "Syllables": [
                        {
                            "Syllable": "herrd",
                            "Grapheme": "heard",
                            "PronunciationAssessment": {
                                "AccuracyScore": 93.0
                            },
                            "Offset": 114700000,
                            "Duration": 6700000
                        }
                    ],
                    "Phonemes": [
                        {
                            "Phoneme": "h",
                            "PronunciationAssessment": {
                                "AccuracyScore": 100.0
                            },
                            "Offset": 114700000,
                            "Duration": 1900000
                        },
                        {
                            "Phoneme": "er",
                            "PronunciationAssessment": {
                                "AccuracyScore": 100.0
                            },
                            "Offset": 116700000,
                            "Duration": 1000000
                        },
                        {
                            "Phoneme": "r",
                            "PronunciationAssessment": {
                                "AccuracyScore": 100.0
                            },
                            "Offset": 117800000,
                            "Duration": 1400000
                        },
                        {
                            "Phoneme": "d",
                            "PronunciationAssessment": {
                                "AccuracyScore": 77.0
                            },
                            "Offset": 119300000,
                            "Duration": 2100000
                        }
                    ]
                },
                {
                    "Word": "and",
                    "Offset": 122500000,
                    "Duration": 2200000,
                    "PronunciationAssessment": {
                        "AccuracyScore": 80.0,
                        "ErrorType": "None"
                    },
                    "Syllables": [
                        {
                            "Syllable": "axnd",
                            "Grapheme": "and",
                            "PronunciationAssessment": {
                                "AccuracyScore": 66.0
                            },
                            "Offset": 122500000,
                            "Duration": 2200000
                        }
                    ],
                    "Phonemes": [
                        {
                            "Phoneme": "ax",
                            "PronunciationAssessment": {
                                "AccuracyScore": 80.0
                            },
                            "Offset": 122500000,
                            "Duration": 1400000
                        },
                        {
                            "Phoneme": "n",
                            "PronunciationAssessment": {
                                "AccuracyScore": 40.0
                            },
                            "Offset": 124000000,
                            "Duration": 200000
                        },
                        {
                            "Phoneme": "d",
                            "PronunciationAssessment": {
                                "AccuracyScore": 40.0
                            },
                            "Offset": 124300000,
                            "Duration": 400000
                        }
                    ]
                },
                {
                    "Word": "given",
                    "Offset": 124800000,
                    "Duration": 4400000,
                    "PronunciationAssessment": {
                        "AccuracyScore": 76.0,
                        "ErrorType": "None"
                    },
                    "Syllables": [
                        {
                            "Syllable": "gih",
                            "Grapheme": "giv",
                            "PronunciationAssessment": {
                                "AccuracyScore": 70.0
                            },
                            "Offset": 124800000,
                            "Duration": 2400000
                        },
                        {
                            "Syllable": "vaxn",
                            "Grapheme": "en",
                            "PronunciationAssessment": {
                                "AccuracyScore": 80.0
                            },
                            "Offset": 127300000,
                            "Duration": 1900000
                        }
                    ],
                    "Phonemes": [
                        {
                            "Phoneme": "g",
                            "PronunciationAssessment": {
                                "AccuracyScore": 66.0
                            },
                            "Offset": 124800000,
                            "Duration": 1400000
                        },
                        {
                            "Phoneme": "ih",
                            "PronunciationAssessment": {
                                "AccuracyScore": 77.0
                            },
                            "Offset": 126300000,
                            "Duration": 900000
                        },
                        {
                            "Phoneme": "v",
                            "PronunciationAssessment": {
                                "AccuracyScore": 96.0
                            },
                            "Offset": 127300000,
                            "Duration": 700000
                        },
                        {
                            "Phoneme": "ax",
                            "PronunciationAssessment": {
                                "AccuracyScore": 90.0
                            },
                            "Offset": 128100000,
                            "Duration": 500000
                        },
                        {
                            "Phoneme": "n",
                            "PronunciationAssessment": {
                                "AccuracyScore": 50.0
                            },
                            "Offset": 128700000,
                            "Duration": 500000
                        }
                    ]
                },
                {
                    "Word": "some",
                    "Offset": 129300000,
                    "Duration": 3500000,
                    "PronunciationAssessment": {
                        "AccuracyScore": 100.0,
                        "ErrorType": "None"
                    },
                    "Syllables": [
                        {
                            "Syllable": "sahm",
                            "Grapheme": "some",
                            "PronunciationAssessment": {
                                "AccuracyScore": 100.0
                            },
                            "Offset": 129300000,
                            "Duration": 3500000
                        }
                    ],
                    "Phonemes": [
                        {
                            "Phoneme": "s",
                            "PronunciationAssessment": {
                                "AccuracyScore": 100.0
                            },
                            "Offset": 129300000,
                            "Duration": 1300000
                        },
                        {
                            "Phoneme": "ah",
                            "PronunciationAssessment": {
                                "AccuracyScore": 100.0
                            },
                            "Offset": 130700000,
                            "Duration": 900000
                        },
                        {
                            "Phoneme": "m",
                            "PronunciationAssessment": {
                                "AccuracyScore": 100.0
                            },
                            "Offset": 131700000,
                            "Duration": 1100000
                        }
                    ]
                },
                {
                    "Word": "meat",
                    "Offset": 132900000,
                    "Duration": 5300000,
                    "PronunciationAssessment": {
                        "AccuracyScore": 100.0,
                        "ErrorType": "None"
                    },
                    "Syllables": [
                        {
                            "Syllable": "miyt",
                            "Grapheme": "meat",
                            "PronunciationAssessment": {
                                "AccuracyScore": 100.0
                            },
                            "Offset": 132900000,
                            "Duration": 5300000
                        }
                    ],
                    "Phonemes": [
                        {
                            "Phoneme": "m",
                            "PronunciationAssessment": {
                                "AccuracyScore": 100.0
                            },
                            "Offset": 132900000,
                            "Duration": 900000
                        },
                        {
                            "Phoneme": "iy",
                            "PronunciationAssessment": {
                                "AccuracyScore": 100.0
                            },
                            "Offset": 133900000,
                            "Duration": 1100000
                        },
                        {
                            "Phoneme": "t",
                            "PronunciationAssessment": {
                                "AccuracyScore": 100.0
                            },
                            "Offset": 135100000,
                            "Duration": 3100000
                        }
                    ]
                },
                {
                    "Word": "the",
                    "Offset": 140500000,
                    "Duration": 1700000,
                    "PronunciationAssessment": {
                        "AccuracyScore": 98.0,
                        "ErrorType": "None"
                    },
                    "Syllables": [
                        {
                            "Syllable": "dhax",
                            "Grapheme": "the",
                            "PronunciationAssessment": {
                                "AccuracyScore": 87.0
                            },
                            "Offset": 140500000,
                            "Duration": 1700000
                        }
                    ],
                    "Phonemes": [
                        {
                            "Phoneme": "dh",
                            "PronunciationAssessment": {
                                "AccuracyScore": 88.0
                            },
                            "Offset": 140500000,
                            "Duration": 1100000
                        },
                        {
                            "Phoneme": "ax",
                            "PronunciationAssessment": {
                                "AccuracyScore": 85.0
                            },
                            "Offset": 141700000,
                            "Duration": 500000
                        }
                    ]
                },
                {
                    "Word": "polish",
                    "Offset": 142300000,
                    "Duration": 5300000,
                    "PronunciationAssessment": {
                        "AccuracyScore": 52.0,
                        "ErrorType": "Mispronunciation"
                    },
                    "Syllables": [
                        {
                            "Syllable": "paa",
                            "PronunciationAssessment": {
                                "AccuracyScore": 80.0
                            },
                            "Offset": 142300000,
                            "Duration": 2300000
                        },
                        {
                            "Syllable": "lihsh",
                            "PronunciationAssessment": {
                                "AccuracyScore": 39.0
                            },
                            "Offset": 144700000,
                            "Duration": 2900000
                        }
                    ],
                    "Phonemes": [
                        {
                            "Phoneme": "p",
                            "PronunciationAssessment": {
                                "AccuracyScore": 100.0
                            },
                            "Offset": 142300000,
                            "Duration": 1300000
                        },
                        {
                            "Phoneme": "aa",
                            "PronunciationAssessment": {
                                "AccuracyScore": 52.0
                            },
                            "Offset": 143700000,
                            "Duration": 900000
                        },
                        {
                            "Phoneme": "l",
                            "PronunciationAssessment": {
                                "AccuracyScore": 20.0
                            },
                            "Offset": 144700000,
                            "Duration": 1100000
                        },
                        {
                            "Phoneme": "ih",
                            "PronunciationAssessment": {
                                "AccuracyScore": 49.0
                            },
                            "Offset": 145900000,
                            "Duration": 700000
                        },
                        {
                            "Phoneme": "sh",
                            "PronunciationAssessment": {
                                "AccuracyScore": 53.0
                            },
                            "Offset": 146700000,
                            "Duration": 900000
                        }
                    ]
                },
                {
                    "Word": "dog",
                    "Offset": 147700000,
                    "Duration": 2100000,
                    "PronunciationAssessment": {
                        "AccuracyScore": 70.0,
                        "ErrorType": "None"
                    },
                    "Syllables": [
                        {
                            "Syllable": "daag",
                            "Grapheme": "dog",
                            "PronunciationAssessment": {
                                "AccuracyScore": 72.0
                            },
                            "Offset": 147700000,
                            "Duration": 2100000
                        }
                    ],
                    "Phonemes": [
                        {
                            "Phoneme": "d",
                            "PronunciationAssessment": {
                                "AccuracyScore": 42.0
                            },
                            "Offset": 147700000,
                            "Duration": 700000
                        },
                        {
                            "Phoneme": "aa",
                            "PronunciationAssessment": {
                                "AccuracyScore": 75.0
                            },
                            "Offset": 148500000,
                            "Duration": 500000
                        },
                        {
                            "Phoneme": "g",
                            "PronunciationAssessment": {
                                "AccuracyScore": 100.0
                            },
                            "Offset": 149100000,
                            "Duration": 700000
                        }
                    ]
                },
                {
                    "Word": "replies",
                    "Offset": 149900000,
                    "Duration": 8400000,
                    "PronunciationAssessment": {
                        "AccuracyScore": 98.0,
                        "ErrorType": "None"
                    },
                    "Syllables": [
                        {
                            "Syllable": "rax",
                            "Grapheme": "re",
                            "PronunciationAssessment": {
                                "AccuracyScore": 92.0
                            },
                            "Offset": 149900000,
                            "Duration": 1500000
                        },
                        {
                            "Syllable": "playz",
                            "Grapheme": "plies",
                            "PronunciationAssessment": {
                                "AccuracyScore": 93.0
                            },
                            "Offset": 151500000,
                            "Duration": 6800000
                        }
                    ],
                    "Phonemes": [
                        {
                            "Phoneme": "r",
                            "PronunciationAssessment": {
                                "AccuracyScore": 79.0
                            },
                            "Offset": 149900000,
                            "Duration": 500000
                        },
                        {
                            "Phoneme": "ax",
                            "PronunciationAssessment": {
                                "AccuracyScore": 100.0
                            },
                            "Offset": 150500000,
                            "Duration": 900000
                        },
                        {
                            "Phoneme": "p",
                            "PronunciationAssessment": {
                                "AccuracyScore": 100.0
                            },
                            "Offset": 151500000,
                            "Duration": 900000
                        },
                        {
                            "Phoneme": "l",
                            "PronunciationAssessment": {
                                "AccuracyScore": 100.0
                            },
                            "Offset": 152500000,
                            "Duration": 1300000
                        },
                        {
                            "Phoneme": "ay",
                            "PronunciationAssessment": {
                                "AccuracyScore": 100.0
                            },
                            "Offset": 153900000,
                            "Duration": 1100000
                        },
                        {
                            "Phoneme": "z",
                            "PronunciationAssessment": {
                                "AccuracyScore": 86.0
                            },
                            "Offset": 155100000,
                            "Duration": 3200000
                        }
                    ]
                },
                {
                    "Word": "what",
                    "Offset": 158600000,
                    "Duration": 2600000,
                    "PronunciationAssessment": {
                        "AccuracyScore": 100.0,
                        "ErrorType": "None"
                    },
                    "Syllables": [
                        {
                            "Syllable": "waxt",
                            "Grapheme": "what",
                            "PronunciationAssessment": {
                                "AccuracyScore": 100.0
                            },
                            "Offset": 158600000,
                            "Duration": 2600000
                        }
                    ],
                    "Phonemes": [
                        {
                            "Phoneme": "w",
                            "PronunciationAssessment": {
                                "AccuracyScore": 100.0
                            },
                            "Offset": 158600000,
                            "Duration": 1600000
                        },
                        {
                            "Phoneme": "ax",
                            "PronunciationAssessment": {
                                "AccuracyScore": 100.0
                            },
                            "Offset": 160300000,
                            "Duration": 500000
                        },
                        {
                            "Phoneme": "t",
                            "PronunciationAssessment": {
                                "AccuracyScore": 100.0
                            },
                            "Offset": 160900000,
                            "Duration": 300000
                        }
                    ]
                },
                {
                    "Word": "is",
                    "Offset": 161300000,
                    "Duration": 1700000,
                    "PronunciationAssessment": {
                        "AccuracyScore": 100.0,
                        "ErrorType": "None"
                    },
                    "Syllables": [
                        {
                            "Syllable": "ihz",
                            "Grapheme": "is",
                            "PronunciationAssessment": {
                                "AccuracyScore": 100.0
                            },
                            "Offset": 161300000,
                            "Duration": 1700000
                        }
                    ],
                    "Phonemes": [
                        {
                            "Phoneme": "ih",
                            "PronunciationAssessment": {
                                "AccuracyScore": 100.0
                            },
                            "Offset": 161300000,
                            "Duration": 500000
                        },
                        {
                            "Phoneme": "z",
                            "PronunciationAssessment": {
                                "AccuracyScore": 100.0
                            },
                            "Offset": 161900000,
                            "Duration": 1100000
                        }
                    ]
                },
                {
                    "Word": "meat",
                    "Offset": 163100000,
                    "Duration": 6100000,
                    "PronunciationAssessment": {
                        "AccuracyScore": 100.0,
                        "ErrorType": "None"
                    },
                    "Syllables": [
                        {
                            "Syllable": "miyt",
                            "Grapheme": "meat",
                            "PronunciationAssessment": {
                                "AccuracyScore": 100.0
                            },
                            "Offset": 163100000,
                            "Duration": 6100000
                        }
                    ],
                    "Phonemes": [
                        {
                            "Phoneme": "m",
                            "PronunciationAssessment": {
                                "AccuracyScore": 100.0
                            },
                            "Offset": 163100000,
                            "Duration": 1700000
                        },
                        {
                            "Phoneme": "iy",
                            "PronunciationAssessment": {
                                "AccuracyScore": 100.0
                            },
                            "Offset": 164900000,
                            "Duration": 1400000
                        },
                        {
                            "Phoneme": "t",
                            "PronunciationAssessment": {
                                "AccuracyScore": 100.0
                            },
                            "Offset": 166400000,
                            "Duration": 2800000
                        }
                    ]
                },
                {
                    "Word": "the",
                    "Offset": 170500000,
                    "Duration": 1900000,
                    "PronunciationAssessment": {
                        "AccuracyScore": 100.0,
                        "ErrorType": "None"
                    },
                    "Syllables": [
                        {
                            "Syllable": "dhax",
                            "Grapheme": "the",
                            "PronunciationAssessment": {
                                "AccuracyScore": 100.0
                            },
                            "Offset": 170500000,
                            "Duration": 1900000
                        }
                    ],
                    "Phonemes": [
                        {
                            "Phoneme": "dh",
                            "PronunciationAssessment": {
                                "AccuracyScore": 100.0
                            },
                            "Offset": 170500000,
                            "Duration": 1100000
                        },
                        {
                            "Phoneme": "ax",
                            "PronunciationAssessment": {
                                "AccuracyScore": 100.0
                            },
                            "Offset": 171700000,
                            "Duration": 700000
                        }
                    ]
                },
                {
                    "Word": "soviet",
                    "Offset": 172500000,
                    "Duration": 4300000,
                    "PronunciationAssessment": {
                        "AccuracyScore": 98.0,
                        "ErrorType": "None"
                    },
                    "Syllables": [
                        {
                            "Syllable": "sow",
                            "Grapheme": "so",
                            "PronunciationAssessment": {
                                "AccuracyScore": 93.0
                            },
                            "Offset": 172500000,
                            "Duration": 1900000
                        },
                        {
                            "Syllable": "viy",
                            "Grapheme": "vi",
                            "PronunciationAssessment": {
                                "AccuracyScore": 100.0
                            },
                            "Offset": 174500000,
                            "Duration": 1200000
                        },
                        {
                            "Syllable": "axt",
                            "Grapheme": "et",
                            "PronunciationAssessment": {
                                "AccuracyScore": 88.0
                            },
                            "Offset": 175800000,
                            "Duration": 1000000
                        }
                    ],
                    "Phonemes": [
                        {
                            "Phoneme": "s",
                            "PronunciationAssessment": {
                                "AccuracyScore": 88.0
                            },
                            "Offset": 172500000,
                            "Duration": 1100000
                        },
                        {
                            "Phoneme": "ow",
                            "PronunciationAssessment": {
                                "AccuracyScore": 100.0
                            },
                            "Offset": 173700000,
                            "Duration": 700000
                        },
                        {
                            "Phoneme": "v",
                            "PronunciationAssessment": {
                                "AccuracyScore": 100.0
                            },
                            "Offset": 174500000,
                            "Duration": 700000
                        },
                        {
                            "Phoneme": "iy",
                            "PronunciationAssessment": {
                                "AccuracyScore": 100.0
                            },
                            "Offset": 175300000,
                            "Duration": 400000
                        },
                        {
                            "Phoneme": "ax",
                            "PronunciationAssessment": {
                                "AccuracyScore": 100.0
                            },
                            "Offset": 175800000,
                            "Duration": 600000
                        },
                        {
                            "Phoneme": "t",
                            "PronunciationAssessment": {
                                "AccuracyScore": 66.0
                            },
                            "Offset": 176500000,
                            "Duration": 300000
                        }
                    ]
                },
                {
                    "Word": "dog",
                    "Offset": 176900000,
                    "Duration": 2300000,
                    "PronunciationAssessment": {
                        "AccuracyScore": 100.0,
                        "ErrorType": "None"
                    },
                    "Syllables": [
                        {
                            "Syllable": "daog",
                            "Grapheme": "dog",
                            "PronunciationAssessment": {
                                "AccuracyScore": 100.0
                            },
                            "Offset": 176900000,
                            "Duration": 2300000
                        }
                    ],
                    "Phonemes": [
                        {
                            "Phoneme": "d",
                            "PronunciationAssessment": {
                                "AccuracyScore": 100.0
                            },
                            "Offset": 176900000,
                            "Duration": 700000
                        },
                        {
                            "Phoneme": "ao",
                            "PronunciationAssessment": {
                                "AccuracyScore": 100.0
                            },
                            "Offset": 177700000,
                            "Duration": 600000
                        },
                        {
                            "Phoneme": "g",
                            "PronunciationAssessment": {
                                "AccuracyScore": 100.0
                            },
                            "Offset": 178400000,
                            "Duration": 800000
                        }
                    ]
                },
                {
                    "Word": "says",
                    "Offset": 179300000,
                    "Duration": 6200000,
                    "PronunciationAssessment": {
                        "AccuracyScore": 100.0,
                        "ErrorType": "None"
                    },
                    "Syllables": [
                        {
                            "Syllable": "sehz",
                            "Grapheme": "says",
                            "PronunciationAssessment": {
                                "AccuracyScore": 100.0
                            },
                            "Offset": 179300000,
                            "Duration": 6200000
                        }
                    ],
                    "Phonemes": [
                        {
                            "Phoneme": "s",
                            "PronunciationAssessment": {
                                "AccuracyScore": 100.0
                            },
                            "Offset": 179300000,
                            "Duration": 1500000
                        },
                        {
                            "Phoneme": "eh",
                            "PronunciationAssessment": {
                                "AccuracyScore": 100.0
                            },
                            "Offset": 180900000,
                            "Duration": 1900000
                        },
                        {
                            "Phoneme": "z",
                            "PronunciationAssessment": {
                                "AccuracyScore": 100.0
                            },
                            "Offset": 182900000,
                            "Duration": 2600000
                        }
                    ]
                },
                {
                    "Word": "what",
                    "Offset": 186400000,
                    "Duration": 1800000,
                    "PronunciationAssessment": {
                        "AccuracyScore": 94.0,
                        "ErrorType": "None"
                    },
                    "Syllables": [
                        {
                            "Syllable": "waxt",
                            "Grapheme": "what",
                            "PronunciationAssessment": {
                                "AccuracyScore": 67.0
                            },
                            "Offset": 186400000,
                            "Duration": 1800000
                        }
                    ],
                    "Phonemes": [
                        {
                            "Phoneme": "w",
                            "PronunciationAssessment": {
                                "AccuracyScore": 56.0
                            },
                            "Offset": 186400000,
                            "Duration": 800000
                        },
                        {
                            "Phoneme": "ax",
                            "PronunciationAssessment": {
                                "AccuracyScore": 66.0
                            },
                            "Offset": 187300000,
                            "Duration": 300000
                        },
                        {
                            "Phoneme": "t",
                            "PronunciationAssessment": {
                                "AccuracyScore": 84.0
                            },
                            "Offset": 187700000,
                            "Duration": 500000
                        }
                    ]
                },
                {
                    "Word": "is",
                    "Offset": 188300000,
                    "Duration": 1500000,
                    "PronunciationAssessment": {
                        "AccuracyScore": 100.0,
                        "ErrorType": "None"
                    },
                    "Syllables": [
                        {
                            "Syllable": "ihz",
                            "Grapheme": "is",
                            "PronunciationAssessment": {
                                "AccuracyScore": 100.0
                            },
                            "Offset": 188300000,
                            "Duration": 1500000
                        }
                    ],
                    "Phonemes": [
                        {
                            "Phoneme": "ih",
                            "PronunciationAssessment": {
                                "AccuracyScore": 100.0
                            },
                            "Offset": 188300000,
                            "Duration": 300000
                        },
                        {
                            "Phoneme": "z",
                            "PronunciationAssessment": {
                                "AccuracyScore": 100.0
                            },
                            "Offset": 188700000,
                            "Duration": 1100000
                        }
                    ]
                },
                {
                    "Word": "bark",
                    "Offset": 189900000,
                    "Duration": 5700000,
                    "PronunciationAssessment": {
                        "AccuracyScore": 100.0,
                        "ErrorType": "None"
                    },
                    "Syllables": [
                        {
                            "Syllable": "baark",
                            "Grapheme": "bark",
                            "PronunciationAssessment": {
                                "AccuracyScore": 100.0
                            },
                            "Offset": 189900000,
                            "Duration": 5700000
                        }
                    ],
                    "Phonemes": [
                        {
                            "Phoneme": "b",
                            "PronunciationAssessment": {
                                "AccuracyScore": 100.0
                            },
                            "Offset": 189900000,
                            "Duration": 900000
                        },
                        {
                            "Phoneme": "aa",
                            "PronunciationAssessment": {
                                "AccuracyScore": 100.0
                            },
                            "Offset": 190900000,
                            "Duration": 1100000
                        },
                        {
                            "Phoneme": "r",
                            "PronunciationAssessment": {
                                "AccuracyScore": 100.0
                            },
                            "Offset": 192100000,
                            "Duration": 1300000
                        },
                        {
                            "Phoneme": "k",
                            "PronunciationAssessment": {
                                "AccuracyScore": 100.0
                            },
                            "Offset": 193500000,
                            "Duration": 2100000
                        }
                    ]
                }
            ]
        }
    ]
}